assistants/auto.py
assistants/log_status.py
assistants/compliance/calculation_logic.py
assistants/compliance/compliance_assistant.py
assistants/compliance/summary_statistics.py
assistants/compliance/cleaning/canonicalisation.py
assistants/compliance/cleaning/fix_compliance_dates.py
assistants/compliance/cleaning/preprocessing.py
assistants/compliance/cleaning/roles_to_requirements.py
assistants/compliance/util/fields.py
assistants/compliance/util/input_data_utility.py
assistants/data/r2r_sep_20.csv
assistants/data/translation_sep_20.csv
assistants/region_bulletins/aggregate.py
assistants/region_bulletins/narrative_text.py
assistants/region_bulletins/region_bulletin.py
assistants/region_bulletins/supporting_data.py
assistants/training/canonicalisation.py
assistants/training/fields.py
assistants/utility/excel_interface.py
assistants/utility/extract_join.py
assistants-2.1.0.dist-info/LICENSE
assistants-2.1.0.dist-info/METADATA
assistants-2.1.0.dist-info/WHEEL
assistants-2.1.0.dist-info/top_level.txt
assistants-2.1.0.dist-info/RECORD
