Metadata-Version: 2.1
Name: assistants
Version: 2.1.0
Summary: Reporting assistants for scouts
Home-page: https://github.com/the-scouts/assistants
Author: Adam Turner
License: MIT
Keywords: reporting,assistants,scouts
Platform: any
Classifier: Development Status :: 4 - Beta
Classifier: Intended Audience :: Developers
Classifier: License :: OSI Approved :: MIT License
Classifier: Operating System :: OS Independent
Classifier: Programming Language :: Python :: 3 :: Only
Classifier: Programming Language :: Python :: 3.9
Classifier: Programming Language :: Python :: Implementation :: CPython
Classifier: Programming Language :: Python :: Implementation :: PyPy
Classifier: Topic :: Software Development
Classifier: Topic :: Utilities
Requires-Python: >=3.9
License-File: LICENSE
Requires-Dist: pandas (>=1.2.0)
Requires-Dist: pyarrow
Requires-Dist: openpyxl
Provides-Extra: compass
Requires-Dist: compass-interface-core (>=0.19.0) ; extra == 'compass'
